ForeNameTranslator/__init__.py
ForeNameTranslator/mode/__init__.py
ForeNameTranslator/mode/mode_FNM_Tra.py
ForeNameTranslator/mode/mode_TRA_Api.py
ForeNameTranslator-0.0.1.dist-info/LICENSE
ForeNameTranslator-0.0.1.dist-info/METADATA
ForeNameTranslator-0.0.1.dist-info/WHEEL
ForeNameTranslator-0.0.1.dist-info/top_level.txt
ForeNameTranslator-0.0.1.dist-info/zip-safe
ForeNameTranslator-0.0.1.dist-info/RECORD
