Metadata-Version: 2.1
Name: ForeNameTranslator
Version: 0.0.1
Summary: Tool lib of network for Love Book Store Volunteer Association of NWAFU by Matt Belfast Brown
Home-page: https://github.com/thedayofthedoctor/fnt
Author: Matt Belfast Brown
Author-email: thedayofthedo@gmail.com
License: GPL-3.0 LICENSE
Project-URL: Documentation, http://belfast.web3v.work/program/doc/fnt/
Project-URL: Bug Tracker, https://github.com/thedayofthedoctor/fnt/issues
Keywords: pip,name,translator
Platform: any
Classifier: Programming Language :: Python :: 3.7
Classifier: Programming Language :: Python :: 3.8
Classifier: Programming Language :: Python :: 3.9
Classifier: Programming Language :: Python :: 3.10
Classifier: Programming Language :: Python :: 3.11
Classifier: Programming Language :: Python :: 3.12
Classifier: License :: OSI Approved :: GNU General Public License v3 (GPLv3)
Requires-Python: >=3.7,<=3.12
License-File: LICENSE
Requires-Dist: requests
